{"repo": {"name": {"en-US": "Nova AI"}, "description": {"en-US": "Nova AI - Privacy-focused AI chat client with tool calling, vision, and web search."}, "icon": {"en-US": {"name": "/icons/icon.png", "sha256": "daedbc7f91ca266a45c2d612721a9aef0b345bc3549cc9141e5f1aaea47516ee", "size": 799}}, "address": "https://loak7993-code.github.io/nova-ai-fdroid/repo", "timestamp": 1784849137000, "categories": {"Internet": {"name": {"en-US": "Internet"}}, "Science & Education": {"name": {"en-US": "Science & Education"}}}}, "packages": {"com.nova.ai": {"metadata": {"added": 1784848330000, "categories": ["Internet", "Science & Education"], "issueTracker": "https://github.com/loak7993-code/nova-ai/issues", "lastUpdated": 1784848330000, "license": "GPL-3.0-or-later", "sourceCode": "https://github.com/loak7993-code/nova-ai", "webSite": "https://github.com/loak7993-code/nova-ai", "authorName": "loak7993-code", "name": {"en-US": "Nova AI"}, "summary": {"en-US": "Privacy-focused AI chat with tool calling and web search"}, "description": {"en-US": "Nova AI is a privacy-focused Android AI chat client supporting multiple\nLLM models via the W&B Inference API.\n\nFeatures:\n* Multi-model: GLM-5.2, MiniMax M3, Kimi K2.7 Code\n* Streaming with reasoning/thinking display\n* Tool calling: calculator, time, web search (SearXNG)\n* Image vision (Kimi K2.7 Code, MiniMax M3)\n* Markdown with tables, code blocks, lists\n* No tracking, no ads, no proprietary SDKs\n"}, "icon": {"en-US": {"name": "/icons/com.nova.ai.15.png", "sha256": "69441cef683d6f3ad81780e2af8381b9591a090a8d46aa2260b61fff7b884396", "size": 2033}}, "preferredSigner": "ffaf463832590e8806886c10000b7206842df5c3c8a41473b6c139adbb892c05"}, "versions": {"3a1c129887ce8ba4bc8df46b022aa80718c711db9dcff8a41484c25e8727d0fe": {"added": 1784848330000, "file": {"name": "/com.nova.ai_15.apk", "sha256": "3a1c129887ce8ba4bc8df46b022aa80718c711db9dcff8a41484c25e8727d0fe", "size": 6974399}, "manifest": {"versionName": "2.1", "versionCode": 15, "usesSdk": {"minSdkVersion": 24, "targetSdkVersion": 35}, "signer": {"sha256": ["ffaf463832590e8806886c10000b7206842df5c3c8a41473b6c139adbb892c05"]}, "usesPermission": [{"name": "android.permission.INTERNET"}, {"name": "android.permission.ACCESS_NETWORK_STATE"}, {"name": "android.permission.VIBRATE"}, {"name": "android.permission.CLIPBOARD"}, {"name": "com.nova.ai.DYNAMIC_RECEIVER_NOT_EXPORTED_PERMISSION"}]}}}}}}